{
    "sourceFile": "src/components/Sidebar.jsx",
    "activeCommit": 0,
    "commits": [
        {
            "activePatchIndex": 5,
            "patches": [
                {
                    "date": 1772450736245,
                    "content": "Index: \n===================================================================\n--- \n+++ \n"
                },
                {
                    "date": 1772450740548,
                    "content": "Index: \n===================================================================\n--- \n+++ \n@@ -203,9 +203,9 @@\n                 <ListItemButton\r\n                   selected={location.pathname.includes('/diff')}\r\n                   onClick={() =>\r\n               //      navigate(`/projects/${projectKey}/diff`) for integratiom with diff viewer\r\n-                      navigate(`/p/diff)\r\n+                      navigate(`/diff)\r\n                   }\r\n                   sx={{\r\n                     borderRadius: 2,\r\n                     py: 1.2,\r\n"
                },
                {
                    "date": 1772450776860,
                    "content": "Index: \n===================================================================\n--- \n+++ \n@@ -203,9 +203,9 @@\n                 <ListItemButton\r\n                   selected={location.pathname.includes('/diff')}\r\n                   onClick={() =>\r\n               //      navigate(`/projects/${projectKey}/diff`) for integratiom with diff viewer\r\n-                      navigate(`/diff)\r\n+                      navigate(`/diff`)\r\n                   }\r\n                   sx={{\r\n                     borderRadius: 2,\r\n                     py: 1.2,\r\n"
                },
                {
                    "date": 1772450784288,
                    "content": "Index: \n===================================================================\n--- \n+++ \n@@ -223,9 +223,9 @@\n \r\n                 <ListItemButton\r\n                   selected={location.pathname.includes('/summary')}\r\n                   onClick={() =>\r\n-                    navigate(`/projects/${projectKey}/summary`)\r\n+                  //  navigate(`/projects/${projectKey}/summary`)\r\n                   }\r\n                   sx={{\r\n                     borderRadius: 2,\r\n                     py: 1.2,\r\n"
                },
                {
                    "date": 1772450791653,
                    "content": "Index: \n===================================================================\n--- \n+++ \n@@ -224,8 +224,9 @@\n                 <ListItemButton\r\n                   selected={location.pathname.includes('/summary')}\r\n                   onClick={() =>\r\n                   //  navigate(`/projects/${projectKey}/summary`)\r\n+                  navigate(`/projects/${projectKey}/summary`)\r\n                   }\r\n                   sx={{\r\n                     borderRadius: 2,\r\n                     py: 1.2,\r\n"
                },
                {
                    "date": 1772450797174,
                    "content": "Index: \n===================================================================\n--- \n+++ \n@@ -224,9 +224,9 @@\n                 <ListItemButton\r\n                   selected={location.pathname.includes('/summary')}\r\n                   onClick={() =>\r\n                   //  navigate(`/projects/${projectKey}/summary`)\r\n-                  navigate(`/projects/${projectKey}/summary`)\r\n+                  navigate(`/summary`)\r\n                   }\r\n                   sx={{\r\n                     borderRadius: 2,\r\n                     py: 1.2,\r\n"
                }
            ],
            "date": 1772450736245,
            "name": "Commit-0",
            "content": "import React from 'react';\r\nimport {\r\n  Drawer,\r\n  List,\r\n  ListItem,\r\n  ListItemButton,\r\n  ListItemIcon,\r\n  ListItemText,\r\n  Toolbar,\r\n  Box,\r\n  Typography\r\n} from '@mui/material';\r\n\r\nimport {\r\n  LayoutDashboard,\r\n  FolderOpen,\r\n  Activity,\r\n  LogOut,\r\n  Code\r\n} from 'lucide-react';\r\n\r\nimport { useNavigate, useLocation, useParams } from 'react-router-dom';\r\n\r\nconst drawerWidth = 260;\r\n\r\nconst Sidebar = () => {\r\n  const navigate = useNavigate();\r\n  const location = useLocation();\r\n  const { projectKey } = useParams();\r\n\r\n  const isInsideProject = location.pathname.startsWith('/projects/');\r\n\r\n  const menuItems = [\r\n    {\r\n      text: 'Dashboard',\r\n      icon: <LayoutDashboard size={20} />,\r\n      path: '/dashboard'\r\n    },\r\n    {\r\n      text: 'Upload Project',\r\n      icon: <FolderOpen size={20} />,\r\n      path: '/upload'\r\n    },\r\n    {\r\n      text: 'Scan Status',\r\n      icon: <Activity size={20} />,\r\n      path: '/scan-status'\r\n    }\r\n  ];\r\n\r\n  return (\r\n    <Drawer\r\n      variant=\"permanent\"\r\n      sx={{\r\n        width: drawerWidth,\r\n        flexShrink: 0,\r\n        [`& .MuiDrawer-paper`]: {\r\n          width: drawerWidth,\r\n          boxSizing: 'border-box',\r\n          borderRight: 'none',\r\n          backgroundColor: '#1a1b23',\r\n          color: '#94a3b8',\r\n          display: 'flex',\r\n          flexDirection: 'column'\r\n        }\r\n      }}\r\n    >\r\n      {/* LOGO */}\r\n      <Toolbar sx={{ minHeight: '84px !important', px: 3 }}>\r\n        <Box sx={{ display: 'flex', alignItems: 'center', gap: 1.5 }}>\r\n          <Box\r\n            sx={{\r\n              width: 32,\r\n              height: 32,\r\n              bgcolor: '#2563eb',\r\n              borderRadius: 1.25,\r\n              display: 'flex',\r\n              alignItems: 'center',\r\n              justifyContent: 'center'\r\n            }}\r\n          >\r\n            <Code color=\"white\" size={20} strokeWidth={2.5} />\r\n          </Box>\r\n          <Typography\r\n            variant=\"h6\"\r\n            sx={{\r\n              color: '#fff',\r\n              fontWeight: 700,\r\n              letterSpacing: '-0.02em',\r\n              fontSize: '1.25rem'\r\n            }}\r\n          >\r\n            SonarFix\r\n          </Typography>\r\n        </Box>\r\n      </Toolbar>\r\n\r\n      {/* MAIN MENU */}\r\n      <Box sx={{ overflow: 'auto', py: 2, flex: 1 }}>\r\n        <List sx={{ px: 2 }}>\r\n          {menuItems.map(item => {\r\n            const isSelected = location.pathname.startsWith(item.path);\r\n\r\n            return (\r\n              <ListItem key={item.text} disablePadding sx={{ mb: 0.5 }}>\r\n                <ListItemButton\r\n                  selected={isSelected}\r\n                  onClick={() => navigate(item.path)}\r\n                  sx={{\r\n                    borderRadius: 2,\r\n                    py: 1.5,\r\n                    color: isSelected ? '#fff' : '#94a3b8',\r\n                    '&.Mui-selected': {\r\n                      backgroundColor: '#2d2e3a',\r\n                      color: '#fff'\r\n                    },\r\n                    '&:hover': {\r\n                      backgroundColor: '#252630',\r\n                      color: '#fff'\r\n                    }\r\n                  }}\r\n                >\r\n                  <ListItemIcon\r\n                    sx={{\r\n                      color: 'inherit',\r\n                      minWidth: 40\r\n                    }}\r\n                  >\r\n                    {item.icon}\r\n                  </ListItemIcon>\r\n                  <ListItemText\r\n                    primary={item.text}\r\n                    primaryTypographyProps={{\r\n                      fontWeight: isSelected ? 600 : 400,\r\n                      fontSize: '0.9rem'\r\n                    }}\r\n                  />\r\n                </ListItemButton>\r\n              </ListItem>\r\n            );\r\n          })}\r\n\r\n          {/* PROJECT SUB NAV (ONLY WHEN INSIDE PROJECT) */}\r\n          {isInsideProject && projectKey && (\r\n            <>\r\n              <Box\r\n                sx={{\r\n                  borderTop: '1px solid #2d2e3a',\r\n                  mt: 2,\r\n                  pt: 2,\r\n                  px: 2\r\n                }}\r\n              >\r\n                <Typography\r\n                  sx={{\r\n                    fontSize: '0.75rem',\r\n                    color: '#64748b',\r\n                    mb: 1\r\n                  }}\r\n                >\r\n                  PROJECT\r\n                </Typography>\r\n\r\n                <ListItemButton\r\n                  selected={location.pathname.includes('/issues')}\r\n                  onClick={() =>\r\n                    navigate(`/projects/${projectKey}/issues`)\r\n                  }\r\n                  sx={{\r\n                    borderRadius: 2,\r\n                    py: 1.2,\r\n                    color: location.pathname.includes('/issues')\r\n                      ? '#fff'\r\n                      : '#94a3b8',\r\n                    '&:hover': {\r\n                      backgroundColor: '#252630',\r\n                      color: '#fff'\r\n                    }\r\n                  }}\r\n                >\r\n                  <ListItemText primary=\"Issues Explorer\" />\r\n                </ListItemButton>\r\n\r\n                <ListItemButton\r\n                  selected={location.pathname.includes('/code')}\r\n                  onClick={() =>\r\n                    navigate(`/projects/${projectKey}/code`)\r\n                  }\r\n                  sx={{\r\n                    borderRadius: 2,\r\n                    py: 1.2,\r\n                    color: location.pathname.includes('/code')\r\n                      ? '#fff'\r\n                      : '#94a3b8',\r\n                    '&:hover': {\r\n                      backgroundColor: '#252630',\r\n                      color: '#fff'\r\n                    }\r\n                  }}\r\n                >\r\n                  <ListItemText primary=\"Code Viewer\" />\r\n                </ListItemButton>\r\n                <ListItemButton\r\n                  selected={location.pathname.includes('/diff')}\r\n                  onClick={() =>\r\n              //      navigate(`/projects/${projectKey}/diff`) for integratiom with diff viewer\r\n                      navigate(`/p/diff)\r\n                  }\r\n                  sx={{\r\n                    borderRadius: 2,\r\n                    py: 1.2,\r\n                    color: location.pathname.includes('/diff')\r\n                      ? '#fff'\r\n                      : '#94a3b8',\r\n                    '&:hover': {\r\n                      backgroundColor: '#252630',\r\n                      color: '#fff'\r\n                    }\r\n                  }}\r\n                >\r\n                  <ListItemText primary=\"Diff Viewer\" />\r\n                </ListItemButton>\r\n\r\n                <ListItemButton\r\n                  selected={location.pathname.includes('/summary')}\r\n                  onClick={() =>\r\n                    navigate(`/projects/${projectKey}/summary`)\r\n                  }\r\n                  sx={{\r\n                    borderRadius: 2,\r\n                    py: 1.2,\r\n                    color: location.pathname.includes('/summary')\r\n                      ? '#fff'\r\n                      : '#94a3b8',\r\n                    '&:hover': {\r\n                      backgroundColor: '#252630',\r\n                      color: '#fff'\r\n                    }\r\n                  }}\r\n                >\r\n                  <ListItemText primary=\"Summary\" />\r\n                </ListItemButton>\r\n              </Box>\r\n            </>\r\n          )}\r\n        </List>\r\n      </Box>\r\n\r\n      {/* SIGN OUT */}\r\n      <Box sx={{ p: 2 }}>\r\n        <ListItemButton\r\n          onClick={() => {\r\n            localStorage.removeItem('isAuthenticated');\r\n            navigate('/');\r\n          }}\r\n          sx={{\r\n            borderRadius: 2,\r\n            py: 1.5,\r\n            color: '#94a3b8',\r\n            '&:hover': {\r\n              backgroundColor: '#ef4444',\r\n              color: '#fff'\r\n            }\r\n          }}\r\n        >\r\n          <ListItemIcon sx={{ color: 'inherit', minWidth: 40 }}>\r\n            <LogOut size={20} />\r\n          </ListItemIcon>\r\n          <ListItemText\r\n            primary=\"Sign Out\"\r\n            primaryTypographyProps={{\r\n              fontWeight: 500,\r\n              fontSize: '0.875rem'\r\n            }}\r\n          />\r\n        </ListItemButton>\r\n      </Box>\r\n    </Drawer>\r\n  );\r\n};\r\n\r\nexport default Sidebar;"
        }
    ]
}