{
    "sourceFile": "src/pages/SummaryDownload.jsx",
    "activeCommit": 0,
    "commits": [
        {
            "activePatchIndex": 2,
            "patches": [
                {
                    "date": 1772902121443,
                    "content": "Index: \n===================================================================\n--- \n+++ \n"
                },
                {
                    "date": 1772903524933,
                    "content": "Index: \n===================================================================\n--- \n+++ \n@@ -193,5 +193,54 @@\n                   {entry.fixType.replace(/_/g, \" \")}\r\n                 </td>\r\n \r\n                 <td>\r\n-             \n\\ No newline at end of file\n+                  <span className=\"fix-count-badge\">\r\n+                    {entry.count}\r\n+                  </span>\r\n+                </td>\r\n+\r\n+              </tr>\r\n+\r\n+            ))}\r\n+\r\n+          </tbody>\r\n+\r\n+        </table>\r\n+\r\n+      </div>\r\n+\r\n+      <div className=\"summary-action-bar\">\r\n+\r\n+        <span className=\"action-bar-text\">\r\n+          Ready to deploy? Download your refactored project now.\r\n+        </span>\r\n+\r\n+        <div className=\"action-bar-buttons\">\r\n+\r\n+          <button\r\n+            className=\"btn-rescan\"\r\n+            onClick={handleRescan}\r\n+          >\r\n+            <RefreshCw size={16} />\r\n+            Re-scan Project\r\n+          </button>\r\n+\r\n+          <button\r\n+            className=\"btn-download\"\r\n+            onClick={handleDownload}\r\n+          >\r\n+            <Download size={16} />\r\n+            Download Refactored Project\r\n+          </button>\r\n+\r\n+        </div>\r\n+\r\n+      </div>\r\n+\r\n+    </Box>\r\n+\r\n+  );\r\n+\r\n+};\r\n+\r\n+export default SummaryDownload;\n\\ No newline at end of file\n"
                },
                {
                    "date": 1772982698528,
                    "content": "Index: \n===================================================================\n--- \n+++ \n@@ -77,9 +77,9 @@\n   const handleDownload = () => {\r\n \r\n     window.open(\r\n       `http://localhost:8080/api/autofix/download/${projectKey}`,\r\n-      \"_blank\"\r\n+     \r\n     );\r\n \r\n   };\r\n \r\n"
                }
            ],
            "date": 1772902121443,
            "name": "Commit-0",
            "content": "import React, { useEffect, useState } from \"react\";\r\nimport { Box, Typography, CircularProgress } from \"@mui/material\";\r\nimport {\r\n  CheckCircle,\r\n  Download,\r\n  RefreshCw,\r\n  Bug\r\n} from \"lucide-react\";\r\nimport { useNavigate, useParams } from \"react-router-dom\";\r\nimport \"./SummaryDownload.css\";\r\n\r\nconst SummaryDownload = () => {\r\n  const navigate = useNavigate();\r\n  const { projectKey } = useParams();\r\n\r\n  const [loading, setLoading] = useState(true);\r\n\r\n  /* -------- MOCK DATA -------- */\r\n\r\n  const [totalIssues] = useState(28);\r\n  const [totalFixed] = useState(21);\r\n\r\n  const [changeLog] = useState([\r\n    { fixType: \"SQL_INJECTION\", count: 6 },\r\n    { fixType: \"NULL_POINTER\", count: 8 },\r\n    { fixType: \"HARDCODED_CREDENTIALS\", count: 3 },\r\n    { fixType: \"CODE_SMELL\", count: 4 }\r\n  ]);\r\n\r\n  useEffect(() => {\r\n    setTimeout(() => {\r\n      setLoading(false);\r\n    }, 800);\r\n  }, []);\r\n\r\n  const remaining = Math.max(0, totalIssues - totalFixed);\r\n  const successRate =\r\n    totalIssues > 0 ? Math.round((totalFixed / totalIssues) * 100) : 0;\r\n\r\n  /* -------- BUTTON ACTIONS -------- */\r\n\r\n  const handleDownload = () => {\r\n    alert(\"Download triggered (mock download)\");\r\n  };\r\n\r\n  const handleRescan = () => {\r\n    alert(\"Rescan triggered (mock action)\");\r\n  };\r\n\r\n  if (loading) {\r\n    return (\r\n      <Box className=\"summary-loading\">\r\n        <CircularProgress />\r\n      </Box>\r\n    );\r\n  }\r\n\r\n  return (\r\n    <Box sx={{ minHeight: \"100vh\" }}>\r\n\r\n      {/* TITLE */}\r\n\r\n      <div className=\"summary-page-title\">\r\n        <div className=\"title-icon\">\r\n          <CheckCircle size={20} />\r\n        </div>\r\n\r\n        <Typography variant=\"h4\" sx={{ fontWeight: 800 }}>\r\n          Refactoring Summary & Download\r\n        </Typography>\r\n      </div>\r\n\r\n      {/* HERO */}\r\n\r\n      <div className=\"summary-hero\">\r\n\r\n        <div className=\"hero-check-circle\">\r\n          <CheckCircle size={36} />\r\n        </div>\r\n\r\n        <h2>Refactoring Complete!</h2>\r\n\r\n        <p>\r\n          {totalFixed} out of {totalIssues} issues have been successfully fixed\r\n        </p>\r\n\r\n      </div>\r\n\r\n      {/* STATS */}\r\n\r\n      <div className=\"summary-stats-row\">\r\n\r\n        <div className=\"summary-stat-card green\">\r\n\r\n          <div className=\"stat-card-icon green-bg\">\r\n            <CheckCircle size={24} />\r\n          </div>\r\n\r\n          <p className=\"stat-value green\">{totalFixed}</p>\r\n          <p className=\"stat-label\">Issues Fixed</p>\r\n\r\n        </div>\r\n\r\n        <div className=\"summary-stat-card orange\">\r\n\r\n          <div className=\"stat-card-icon orange-bg\">\r\n            <Bug size={24} />\r\n          </div>\r\n\r\n          <p className=\"stat-value orange\">{remaining}</p>\r\n          <p className=\"stat-label\">Remaining Issues</p>\r\n\r\n        </div>\r\n\r\n      </div>\r\n\r\n      {/* CHANGELOG */}\r\n\r\n      <div className=\"summary-changelog\">\r\n\r\n        <h3>Detailed Change Log</h3>\r\n\r\n        <table className=\"changelog-table\">\r\n\r\n          <thead>\r\n            <tr>\r\n              <th>#</th>\r\n              <th>Fix Category</th>\r\n              <th>Fixes Applied</th>\r\n            </tr>\r\n          </thead>\r\n\r\n          <tbody>\r\n\r\n            {changeLog.map((entry, idx) => (\r\n\r\n              <tr key={idx}>\r\n\r\n                <td>{idx + 1}</td>\r\n\r\n                <td>{entry.fixType.replace(/_/g, \" \")}</td>\r\n\r\n                <td>\r\n                  <span className=\"fix-count-badge\">{entry.count}</span>\r\n                </td>\r\n\r\n              </tr>\r\n\r\n            ))}\r\n\r\n          </tbody>\r\n\r\n        </table>\r\n\r\n      </div>\r\n\r\n      {/* ACTION BAR */}\r\n\r\n      <div className=\"summary-action-bar\">\r\n\r\n        <span className=\"action-bar-text\">\r\n          Ready to deploy? Download your refactored project now.\r\n        </span>\r\n\r\n        <div className=\"action-bar-buttons\">\r\n\r\n          <button className=\"btn-rescan\" onClick={handleRescan}>\r\n            <RefreshCw size={16} />\r\n            Re-scan Project\r\n          </button>\r\n\r\n          <button className=\"btn-download\" onClick={handleDownload}>\r\n            <Download size={16} />\r\n            Download Refactored Project\r\n          </button>\r\n\r\n        </div>\r\n\r\n      </div>\r\n\r\n    </Box>\r\n  );\r\n};\r\n\r\nexport default SummaryDownload;\r\n"
        }
    ]
}